osm_bot_abstraction_layer/__init__.py
osm_bot_abstraction_layer/generic_bot_migrate_values_from_single_key_to_simple_tag_sets.py
osm_bot_abstraction_layer/generic_bot_migrate_values_within_key.py
osm_bot_abstraction_layer/generic_bot_migrate_yes_value_to_a_different_key.py
osm_bot_abstraction_layer/generic_bot_retagging.py
osm_bot_abstraction_layer/human_verification_mode.py
osm_bot_abstraction_layer/language_tag_knowledge.py
osm_bot_abstraction_layer/oauth_handling.py
osm_bot_abstraction_layer/osm_bot_abstraction_layer.py
osm_bot_abstraction_layer/overpass_downloader.py
osm_bot_abstraction_layer/overpass_query_maker.py
osm_bot_abstraction_layer/split_into_packages.py
osm_bot_abstraction_layer/tag_knowledge.py
osm_bot_abstraction_layer/util_download_file.py
osm_bot_abstraction_layer/utils.py
osm_bot_abstraction_layer/world_data.py
osm_bot_abstraction_layer-0.0.23.dist-info/licenses/LICENSE
osm_bot_abstraction_layer-0.0.23.dist-info/METADATA
osm_bot_abstraction_layer-0.0.23.dist-info/WHEEL
osm_bot_abstraction_layer-0.0.23.dist-info/top_level.txt
osm_bot_abstraction_layer-0.0.23.dist-info/RECORD
