Metadata-Version: 2.4
Name: osm_bot_abstraction_layer
Version: 0.0.23
Summary: A tool for easier automation of OSM edits without causing problems.
Home-page: https://github.com/matkoniecz/osm_bot_abstraction_layer
Author: Mateusz Konieczny
Author-email: matkoniecz@gmail.com
Classifier: Programming Language :: Python :: 3
Classifier: License :: OSI Approved :: GNU Affero General Public License v3
Classifier: Operating System :: OS Independent
License-File: LICENSE
Requires-Dist: osmapi<5.0,>=4.2.0
Requires-Dist: termcolor<2.0,>=1.1.0
Requires-Dist: requests<3.0,>=2.22.0
Requires-Dist: requests-oauthlib<3.0,>=2.0.0
Requires-Dist: dotenv
Requires-Dist: osm_iterator<2.0,>=1.5.0
Requires-Dist: tqdm<5.0,>4.47.0
Requires-Dist: lxml>=3.5.0
Requires-Dist: urllib3>=1.25.8
Requires-Dist: taginfo>=0.0.3
Dynamic: author
Dynamic: author-email
Dynamic: classifier
Dynamic: description
Dynamic: description-content-type
Dynamic: home-page
Dynamic: license-file
Dynamic: requires-dist
Dynamic: summary
